adif_mcp/__init__.py
adif_mcp/adif_meta.json
adif_mcp/cli/__init__.py
adif_mcp/cli/__main__.py
adif_mcp/cli/root.py
adif_mcp/cli/validate.py
adif_mcp/dev/build_hooks.py
adif_mcp/mcp/manifest.json
adif_mcp/mcp/server.py
adif_mcp/models/__init__.py
adif_mcp/models/entity.py
adif_mcp/models/qso.py
adif_mcp/parsers/adif_reader.py
adif_mcp/resources/__init__.py
adif_mcp/resources/schemas/manifest.v1.json
adif_mcp/resources/spec/adif_catalog.json
adif_mcp/resources/spec/adif_meta.json
adif_mcp/resources/spec/316/all.json
adif_mcp/resources/spec/316/datatypes.json
adif_mcp/resources/spec/316/enumerations.json
adif_mcp/resources/spec/316/enumerations_ant_path.json
adif_mcp/resources/spec/316/enumerations_arrl_section.json
adif_mcp/resources/spec/316/enumerations_award.json
adif_mcp/resources/spec/316/enumerations_award_sponsor.json
adif_mcp/resources/spec/316/enumerations_band.json
adif_mcp/resources/spec/316/enumerations_contest_id.json
adif_mcp/resources/spec/316/enumerations_continent.json
adif_mcp/resources/spec/316/enumerations_credit.json
adif_mcp/resources/spec/316/enumerations_dxcc_entity_code.json
adif_mcp/resources/spec/316/enumerations_eqsl_ag.json
adif_mcp/resources/spec/316/enumerations_mode.json
adif_mcp/resources/spec/316/enumerations_morse_key_type.json
adif_mcp/resources/spec/316/enumerations_primary_administrative_subdivision.json
adif_mcp/resources/spec/316/enumerations_propagation_mode.json
adif_mcp/resources/spec/316/enumerations_qsl_medium.json
adif_mcp/resources/spec/316/enumerations_qsl_rcvd.json
adif_mcp/resources/spec/316/enumerations_qsl_sent.json
adif_mcp/resources/spec/316/enumerations_qsl_via.json
adif_mcp/resources/spec/316/enumerations_qso_complete.json
adif_mcp/resources/spec/316/enumerations_qso_download_status.json
adif_mcp/resources/spec/316/enumerations_qso_upload_status.json
adif_mcp/resources/spec/316/enumerations_region.json
adif_mcp/resources/spec/316/enumerations_secondary_administrative_subdivision.json
adif_mcp-0.6.0.dist-info/METADATA
adif_mcp-0.6.0.dist-info/WHEEL
adif_mcp-0.6.0.dist-info/entry_points.txt
adif_mcp-0.6.0.dist-info/licenses/LICENSE
adif_mcp-0.6.0.dist-info/RECORD
