Metadata-Version: 2.4
Name: adif-mcp
Version: 0.6.0
Summary: ADIF MCP core service with eQSL demo tools
Project-URL: Homepage, https://www.ki7mt.io
Project-URL: Documentation, https://www.ki7mt.io/adif-mcp/
Project-URL: Repository, https://github.com/ki7mt/ki7mt-mcp-hub
Project-URL: Issues, https://github.com/ki7mt/ki7mt-mcp-hub/issues
Author-email: KI7MT <ki7mt@ki7mt.io>
License: MIT
License-File: LICENSE
Classifier: Development Status :: 4 - Beta
Classifier: Intended Audience :: Developers
Classifier: License :: OSI Approved :: MIT License
Classifier: Programming Language :: Python :: 3.10
Classifier: Programming Language :: Python :: 3.11
Classifier: Programming Language :: Python :: 3.12
Classifier: Topic :: Communications :: Ham Radio
Requires-Python: >=3.12
Requires-Dist: aiofiles>=25.1.0
Requires-Dist: anyio>=4.8.0
Requires-Dist: click>=8.1.0
Requires-Dist: commitizen>=3.12.0
Requires-Dist: jsonschema>=4.25.1
Requires-Dist: mcp>=1.2.0
Requires-Dist: typing-extensions
